claim_vet/__init__.py
claim_vet/main.py
claim_vet/prompts.py
claim_vet-2025.12.21083952.dist-info/METADATA
claim_vet-2025.12.21083952.dist-info/WHEEL
claim_vet-2025.12.21083952.dist-info/top_level.txt
claim_vet-2025.12.21083952.dist-info/RECORD
