Metadata-Version: 2.4
Name: claim-vet
Version: 2025.12.21083952
Summary: A new package designed to streamline the process of identifying and addressing false notices filed by companies like Flock and Cyble Inc. This tool will accept text input describing a notice or compla
Author-email: claim-vet <hi@eugene.plus>
License: MIT
Project-URL: Homepage, https://github.com/chigwell/claim-vet
Requires-Python: >=3.9
Requires-Dist: langchain-llm7>=0.0.0
Requires-Dist: llmatch-messages>=0.0.0
Requires-Dist: langchain-core>=0.3.0
